{
  "$schema": "https://mintlify.com/docs.json",
  "name": "Hyperface Documentation",
  "theme": "mint",
  "colors": {
    "primary": "#00D4D4",
    "light": "#38E8E8",
    "dark": "#008B8B"
  },
  "navigation": {
    "groups": [
      {
        "group": "Getting Started",
        "pages": [
          "introduction",
          "getting-started"
        ]
      },
      {
        "group": "Offer Management",
        "pages": [
          {
            "group": "Transactional Offer",
            "pages": [
              "transaction-offer/introduction",
              "transaction-offer/create-transactional-offer",
              "transaction-offer/offer-scope",
              "transaction-offer/offer-user-base",
              "transaction-offer/transaction-eligibility",
              "transaction-offer/offer-calculation",
              "transaction-offer/budget",
              "transaction-offer/usage-limits",
              "transaction-offer/posting",
              "transaction-offer/display-elements",
              "transaction-offer/communication",
              "transaction-offer/sample-configurations"
            ]
          },
          "milestone-offer",
          "merchant-offer",
          "gamified-offer",
          "apple-rewards",
          "rent-cashback",
          "airport-lounge-rewards"
        ]
      }
    ]
  }
}
